{
  "stats": {
    "tconstruct:binding": {},
    "tconstruct:grip": {
      "accuracy": 0.1,
      "durability": 0.95,
      "melee_damage": 1.75
    },
    "tconstruct:handle": {
      "durability": 0.95,
      "melee_damage": 1.0,
      "melee_speed": 1.0,
      "mining_speed": 1.15
    },
    "tconstruct:head": {
      "durability": 675,
      "melee_attack": 1.75,
      "mining_speed": 7.5,
      "mining_tier": "minecraft:diamond"
    },
    "tconstruct:limb": {
      "accuracy": -0.25,
      "draw_speed": 0.2,
      "durability": 675,
      "velocity": -0.05
    }
  }
}